lumby_fbs/BfxTradeType.py
lumby_fbs/NestedOrderUpdate.py
lumby_fbs/NestedOrderUpdateVec.py
lumby_fbs/NestedTradeUpdate.py
lumby_fbs/NestedTradeUpdateVec.py
lumby_fbs/Order.py
lumby_fbs/OrderUpdate.py
lumby_fbs/OrderUpdateVec.py
lumby_fbs/Trade.py
lumby_fbs/TradeUpdate.py
lumby_fbs/TradeUpdateVec.py
lumby_fbs/__init__.py
lumby_fbs-1.0.1.dist-info/METADATA
lumby_fbs-1.0.1.dist-info/WHEEL
lumby_fbs-1.0.1.dist-info/top_level.txt
lumby_fbs-1.0.1.dist-info/RECORD
