Metadata-Version: 2.1
Name: lumby-fbs
Version: 1.0.1
Summary: Lumby flatbuffer schema
Home-page: https://github.com/jean-airoldie/lumby-flatbuffers
Author: Maxence Caron
Author-email: maxence.caron.1@ulaval.ca
License: MIT
Platform: UNKNOWN
Requires-Dist: flatbuffers (==1.10)
